satsp/SAclass.py
satsp/__init__.py
satsp/solver.py
satsp/utilities.py
satsp-0.9.dist-info/METADATA
satsp-0.9.dist-info/RECORD
satsp-0.9.dist-info/WHEEL
satsp-0.9.dist-info/top_level.txt
