Metadata-Version: 2.1
Name: satsp
Version: 0.9
Summary: Travelling Salesman Problem Using Simulated Annealing
Home-page: https://github.com/hcluo/satsp
Author: Haochen Luo
Author-email: hcluo92@gmail.com
License: UNKNOWN
Platform: UNKNOWN
Classifier: Programming Language :: Python :: 3
Classifier: License :: OSI Approved :: MIT License
Classifier: Operating System :: OS Independent
